bella_omni/__init__.py
bella_omni/config.py
bella_omni/router.py
bella_omni/session.py
bella_omni-1.0.0.dist-info/METADATA
bella_omni-1.0.0.dist-info/WHEEL
bella_omni-1.0.0.dist-info/top_level.txt
bella_omni-1.0.0.dist-info/RECORD
